pytest_redis/__init__.py
pytest_redis/config.py
pytest_redis/exception.py
pytest_redis/plugin.py
pytest_redis/py.typed
pytest_redis/executor/__init__.py
pytest_redis/executor/noop.py
pytest_redis/executor/process.py
pytest_redis/factories/__init__.py
pytest_redis/factories/client.py
pytest_redis/factories/noproc.py
pytest_redis/factories/proc.py
pytest_redis-3.1.2.dist-info/COPYING
pytest_redis-3.1.2.dist-info/COPYING.lesser
pytest_redis-3.1.2.dist-info/METADATA
pytest_redis-3.1.2.dist-info/WHEEL
pytest_redis-3.1.2.dist-info/entry_points.txt
pytest_redis-3.1.2.dist-info/top_level.txt
pytest_redis-3.1.2.dist-info/zip-safe
pytest_redis-3.1.2.dist-info/RECORD
