Metadata-Version: 2.1
Name: pytest-redis
Version: 3.1.2
Summary: Redis fixtures and fixture factories for Pytest.
Author-email: Grzegorz Śliwiński <fizyk+pypi@fizyk.dev>
License: GNU LESSER GENERAL PUBLIC LICENSE
Project-URL: Source, https://github.com/ClearcodeHQ/pytest-redis
Project-URL: Bug Tracker, https://github.com/ClearcodeHQ/pytest-redis/issues
Project-URL: Changelog, https://github.com/ClearcodeHQ/pytest-redis/blob/v3.1.2/CHANGES.rst
Keywords: tests,pytest,fixture,redis
Classifier: Development Status :: 5 - Production/Stable
Classifier: Environment :: Web Environment
Classifier: Intended Audience :: Developers
Classifier: License :: OSI Approved :: GNU Lesser General Public License v3 or later (LGPLv3+)
Classifier: Natural Language :: English
Classifier: Operating System :: OS Independent
Classifier: Programming Language :: Python
Classifier: Programming Language :: Python :: 3
Classifier: Programming Language :: Python :: 3.8
Classifier: Programming Language :: Python :: 3.9
Classifier: Programming Language :: Python :: 3.10
Classifier: Programming Language :: Python :: 3.11
Classifier: Programming Language :: Python :: 3.12
Classifier: Programming Language :: Python :: 3 :: Only
Classifier: Topic :: Software Development :: Libraries :: Python Modules
Classifier: Topic :: Software Development :: Testing
Classifier: Framework :: Pytest
Requires-Python: >=3.8
License-File: COPYING
License-File: COPYING.lesser
Requires-Dist: pytest >=6.2
Requires-Dist: port-for >=0.6.0
Requires-Dist: mirakuru
Requires-Dist: redis >=3
